MANIFEST.in
README.md
setup.cfg
setup.py
workerprocess/__init__.py
workerprocess/worker.py
workerprocess.egg-info/PKG-INFO
workerprocess.egg-info/SOURCES.txt
workerprocess.egg-info/dependency_links.txt
workerprocess.egg-info/entry_points.txt
workerprocess.egg-info/top_level.txt
workerprocess.egg-info/zip-safe