Metadata-Version: 1.0
Name: workerprocess
Version: 0.1.2
Summary: A tool for creating external worker processes
Home-page: https://github.com/philipcristiano/worker_process
Author: Philip Cristiano
Author-email: worker_process@philipcristiano.com
License: BSD
Platform: UNKNOWN
Classifier: Development Status :: 2 - Pre-Alpha
Classifier: Intended Audience :: Developers
Classifier: License :: OSI Approved :: BSD License
Classifier: Operating System :: MacOS :: MacOS X
Classifier: Operating System :: POSIX
Classifier: Programming Language :: Python
